praanscribe/__init__.py
praanscribe/praanscribe.py
praanscribe-1.0.2.dist-info/LICENSE
praanscribe-1.0.2.dist-info/METADATA
praanscribe-1.0.2.dist-info/WHEEL
praanscribe-1.0.2.dist-info/entry_points.txt
praanscribe-1.0.2.dist-info/top_level.txt
praanscribe-1.0.2.dist-info/RECORD
